pas/__init__.py
pas/plugins/__init__.py
pas/plugins/authomatic/__init__.py
pas/plugins/authomatic/configure.zcml
pas/plugins/authomatic/interfaces.py
pas/plugins/authomatic/log.py
pas/plugins/authomatic/meta.zcml
pas/plugins/authomatic/plugin.py
pas/plugins/authomatic/profiles.zcml
pas/plugins/authomatic/setuphandlers.py
pas/plugins/authomatic/testing.py
pas/plugins/authomatic/useridentities.py
pas/plugins/authomatic/useridfactories.py
pas/plugins/authomatic/utils.py
pas/plugins/authomatic/browser/__init__.py
pas/plugins/authomatic/browser/add_plugin.pt
pas/plugins/authomatic/browser/authomatic.png
pas/plugins/authomatic/browser/authomatic.pt
pas/plugins/authomatic/browser/configure.zcml
pas/plugins/authomatic/browser/controlpanel.py
pas/plugins/authomatic/browser/view.py
pas/plugins/authomatic/browser/resources/authomatic-logo.svg
pas/plugins/authomatic/browser/resources/authomatic.css
pas/plugins/authomatic/browser/resources/authomatic.less
pas/plugins/authomatic/integration/__init__.py
pas/plugins/authomatic/integration/restapi.py
pas/plugins/authomatic/integration/zope.py
pas/plugins/authomatic/locales/__init__.py
pas/plugins/authomatic/locales/__main__.py
pas/plugins/authomatic/locales/pas.plugins.authomatic-manual.pot
pas/plugins/authomatic/locales/pas.plugins.authomatic.pot
pas/plugins/authomatic/locales/de/LC_MESSAGES/pas.plugins.authomatic.po
pas/plugins/authomatic/locales/es/LC_MESSAGES/pas.plugins.authomatic.po
pas/plugins/authomatic/locales/fr/LC_MESSAGES/pas.plugins.authomatic.po
pas/plugins/authomatic/locales/it/LC_MESSAGES/pas.plugins.authomatic.po
pas/plugins/authomatic/locales/pt_BR/LC_MESSAGES/pas.plugins.authomatic.po
pas/plugins/authomatic/locales/ro/LC_MESSAGES/pas.plugins.authomatic.po
pas/plugins/authomatic/patches/__init__.py
pas/plugins/authomatic/patches/authomatic.py
pas/plugins/authomatic/profiles/default/browserlayer.xml
pas/plugins/authomatic/profiles/default/controlpanel.xml
pas/plugins/authomatic/profiles/default/metadata.xml
pas_plugins_authomatic-2.0.0.dist-info/METADATA
pas_plugins_authomatic-2.0.0.dist-info/WHEEL
pas_plugins_authomatic-2.0.0.dist-info/entry_points.txt
pas_plugins_authomatic-2.0.0.dist-info/licenses/LICENSE.txt
pas_plugins_authomatic-2.0.0.dist-info/RECORD
